ventmap/SAM.py
ventmap/__init__.py
ventmap/breath_meta.py
ventmap/clear_null_bytes.py
ventmap/constants.py
ventmap/cut_breath_section.py
ventmap/detection.py
ventmap/raw_utils.py
ventmap/rounding_rules.py
ventmap-1.0.dist-info/METADATA
ventmap-1.0.dist-info/RECORD
ventmap-1.0.dist-info/WHEEL
ventmap-1.0.dist-info/entry_points.txt
ventmap-1.0.dist-info/top_level.txt
