Metadata-Version: 2.1
Name: ventmap
Version: 1.0
Summary: Ventilator Multi-Analytic Platform for analysis of ventilator waveform data
Home-page: UNKNOWN
Author: UNKNOWN
Author-email: UNKNOWN
License: UNKNOWN
Platform: UNKNOWN
Requires-Dist: numpy
Requires-Dist: pandas
Requires-Dist: scipy
